LICENSE.txt
MANIFEST.in
README.rst
pyproject.toml
setup.py
tutor_minio.egg-info/PKG-INFO
tutor_minio.egg-info/SOURCES.txt
tutor_minio.egg-info/dependency_links.txt
tutor_minio.egg-info/entry_points.txt
tutor_minio.egg-info/requires.txt
tutor_minio.egg-info/top_level.txt
tutorminio/__about__.py
tutorminio/__init__.py
tutorminio/plugin.py
tutorminio/patches/caddyfile
tutorminio/patches/discovery-common-settings
tutorminio/patches/k8s-deployments
tutorminio/patches/k8s-jobs
tutorminio/patches/k8s-services
tutorminio/patches/k8s-volumes
tutorminio/patches/local-docker-compose-caddy-aliases
tutorminio/patches/local-docker-compose-cms-dependencies
tutorminio/patches/local-docker-compose-dev-services
tutorminio/patches/local-docker-compose-jobs-services
tutorminio/patches/local-docker-compose-lms-dependencies
tutorminio/patches/local-docker-compose-services
tutorminio/patches/openedx-auth
tutorminio/patches/openedx-cms-common-settings
tutorminio/patches/openedx-common-settings
tutorminio/patches/openedx-development-settings
tutorminio/patches/openedx-lms-production-settings
tutorminio/patches/richie-settings-common
tutorminio/patches/xqueue-settings
tutorminio/templates/minio/tasks/minio/init.sh